README.rst
setup.py
metriqued/__init__.py
metriqued/basemongodb.py
metriqued/config.py
metriqued/core_api.py
metriqued/cube_api.py
metriqued/query_api.py
metriqued/tornadohttp.py
metriqued/user_api.py
metriqued/utils.py
metriqued.egg-info/PKG-INFO
metriqued.egg-info/SOURCES.txt
metriqued.egg-info/dependency_links.txt
metriqued.egg-info/requires.txt
metriqued.egg-info/top_level.txt