Metadata-Version: 1.1
Name: metriqued
Version: 0.2.6-8a
Summary: Python/MongoDB Information Platform - Server
Home-page: https://github.com/drpoovilleorg/metrique
Author: Chris Ward
Author-email: cward@redhat.com
License: GPLv3
Download-URL: https://github.com/drpoovilleorg/metrique/archive/master.zip
Platform: UNKNOWN
Requires: metriquet (>=0.2.6)
Requires: metriqueu (>=0.2.6)
Requires: gnupg (==1.2.5)
Requires: passlib (==1.6.2)
Requires: pymongo (==2.6.3)
Provides: metriqued
